py_golf_games/__init__.py
py_golf_games/course.py
py_golf_games/games/__init__.py
py_golf_games/games/game.py
py_golf_games/games/game_engine.py
py_golf_games/games/sandie.py
py_golf_games/games/stroke.py
py_golf_games/hole.py
py_golf_games/player.py
py_golf_games/round.py
py_golf_games/scorecard.py
py_golf_games/simulation/__init__.py
py_golf_games/simulation/generator.py
py_golf_games/simulation/simulator.py
py_golf_games/tee.py
py_golf_games-0.1.0.dist-info/WHEEL
py_golf_games-0.1.0.dist-info/METADATA
py_golf_games-0.1.0.dist-info/RECORD
