Metadata-Version: 2.1
Name: py-golf-games
Version: 0.1.0
Summary: Simulation of golf games
Author: Ryan
Author-email: ryankanno@localkinegrinds.com
Requires-Python: >=3.8,<4.0
Classifier: Programming Language :: Python :: 3
Classifier: Programming Language :: Python :: 3.10
Classifier: Programming Language :: Python :: 3.8
Classifier: Programming Language :: Python :: 3.9
